mobilitylabs/__init__.py
mobilitylabs/bicimad.py
mobilitylabs/busemtmad.py
mobilitylabs/core.py
mobilitylabs/parkingemtmad.py
mobilitylabs_bsdprof-0.1.3.dist-info/COPYING
mobilitylabs_bsdprof-0.1.3.dist-info/LICENSE
mobilitylabs_bsdprof-0.1.3.dist-info/METADATA
mobilitylabs_bsdprof-0.1.3.dist-info/WHEEL
mobilitylabs_bsdprof-0.1.3.dist-info/top_level.txt
mobilitylabs_bsdprof-0.1.3.dist-info/RECORD
