Metadata-Version: 2.1
Name: mobilitylabs-bsdprof
Version: 0.1.3
Summary: A Python wrapper for the MobilityLabs Madrid REST API
Home-page: https://github.com/raulmarinperez/mobilitylabs
Author: The BSD Professor
Author-email: me@bsdprof.com
License: UNKNOWN
Project-URL: Bug Tracker, https://github.com/raulmarinperez/mobilitylabs/issues
Platform: UNKNOWN
Classifier: Programming Language :: Python :: 3
Classifier: License :: OSI Approved :: MIT License
Classifier: Operating System :: OS Independent
Requires-Python: >=3.7
Requires-Dist: requests
